refreeze_scripts/__init__.py
refreeze_scripts/cli.py
refreeze_scripts/launcher.py
refreeze_scripts/parser.py
refreeze_scripts/refreezer.py
refreeze_scripts-0.2.0.dist-info/entry_points.txt
refreeze_scripts-0.2.0.dist-info/LICENSE.txt
refreeze_scripts-0.2.0.dist-info/WHEEL
refreeze_scripts-0.2.0.dist-info/METADATA
refreeze_scripts-0.2.0.dist-info/RECORD
