Metadata-Version: 2.1
Name: refreeze-scripts
Version: 0.2.0
Summary: Rewrite EXE files in Scripts directory on Windows
Home-page: https://github.com/fixpoint/refreeze-scripts
License: MIT
Keywords: Windows,pip,setuptools
Author: Fixpoint, Inc.
Author-email: developer@fixpoint.co.jp
Requires-Python: >=3.7,<4.0
Classifier: License :: OSI Approved :: MIT License
Classifier: Programming Language :: Python :: 3
Classifier: Programming Language :: Python :: 3.7
Classifier: Programming Language :: Python :: 3.8
Classifier: Topic :: Software Development :: Build Tools
Requires-Dist: setuptools (>=45.2.0,<46.0.0)
Requires-Dist: typing-extensions (>=3.7.4,<4.0.0)
Project-URL: Repository, https://github.com/fixpoint/refreeze-scripts
